Metadata-Version: 1.0
Name: my-xml
Version: 0.1.1
Summary: Easy to use parser for simple XML
Home-page: UNKNOWN
Author: Erez Bibi
Author-email: erezbibi@users.sourceforge.net
License: UNKNOWN
Keywords: Simple XML Parser
Platform: UNKNOWN
Classifier: Intended Audience :: Developers
Classifier: License :: Public Domain
Classifier: Operating System :: OS Independent
Classifier: Programming Language :: Python
Classifier: Topic :: Text Processing :: Markup :: XML
Classifier: Topic :: Utilities
